h_devops/.gitignore
h_devops/__init__.py
h_devops/__main__.py
h_devops/install/docker.py
h_devops/install/nvm.py
h_devops/main.py
h_devops-0.4.0.dist-info/LICENSE.md
h_devops-0.4.0.dist-info/METADATA
h_devops-0.4.0.dist-info/WHEEL
h_devops-0.4.0.dist-info/entry_points.txt
h_devops-0.4.0.dist-info/RECORD
