Metadata-Version: 2.1
Name: h-devops
Version: 0.4.0
Summary: Tools to assist devops using CLI
Author: Vo Viet Hoang
Author-email: levuthanhtung11@gmail.com
Requires-Python: >=3.7,<4.0
Classifier: Programming Language :: Python :: 3
Classifier: Programming Language :: Python :: 3.7
Classifier: Programming Language :: Python :: 3.8
Classifier: Programming Language :: Python :: 3.9
Classifier: Programming Language :: Python :: 3.10
Classifier: Programming Language :: Python :: 3.11
Requires-Dist: psutil (>=5.9.1,<6.0.0)
Requires-Dist: requests (>=2.31.0,<3.0.0)
Requires-Dist: tabulate (>=0.8.10,<0.9.0)
Requires-Dist: typer[all] (>=0.4.1,<0.5.0)
